LICENSE
MANIFEST.in
README.md
setup.py
libpythonjp/__init__.py
libpythonjp/github_api.py
libpythonjp.egg-info/PKG-INFO
libpythonjp.egg-info/SOURCES.txt
libpythonjp.egg-info/dependency_links.txt
libpythonjp.egg-info/not-zip-safe
libpythonjp.egg-info/requires.txt
libpythonjp.egg-info/top_level.txt