Metadata-Version: 2.1
Name: libpythonjp
Version: 0.2
Summary: Modulo para exemplificar construcapipo de projetos Python para curso Pythontools
Home-page: https://github.com/pythonprgbr/libpythonjp
Author: Jorge Luiz Plautz
Author-email: jorge.plautz@gmail.com
License: GNU AFFERO GENERAL PUBLIC LICENSE
Platform: UNKNOWN
Classifier: Development Status :: 2 - Pre-Alpha
Classifier: Environment :: Console
Classifier: Intended Audience :: Developers
Classifier: License :: OSI Approved :: GNU Lesser General Public License v3 or later (LGPLv3+)
Classifier: Operating System :: OS Independent
Classifier: Programming Language :: Python
Classifier: Programming Language :: Python :: 3.6
Classifier: Framework :: Pytest
